{
  "project_info": {
    "project_number": "323944518260",
    "project_id": "seguridadciudadana-4296f",
    "storage_bucket": "seguridadciudadana-4296f.firebasestorage.app"
  },
  "client": [
    {
      "client_info": {
        "mobilesdk_app_id": "1:323944518260:android:b4fc3451705d122601f721",
        "android_client_info": {
          "package_name": "com.catedra.seguridadciudadana"
        }
      },
      "oauth_client": [],
      "api_key": [
        {
          "current_key": "AIzaSyCdJmEboqX5alvS88ZK3ojrSogpGrH9S2A"
        }
      ],
      "services": {
        "appinvite_service": {
          "other_platform_oauth_client": []
        }
      }
    }
  ],
  "configuration_version": "1"
}